{
    "id": "1015024047c246d78d93c6b5e85d4723",
    "name": "Paulette Boucher de la Daniel",
    "email": "suzannebruneau@example.com",
    "username": "pineauthierry",
    "job": "déménageur",
    "gender": "Femme",
    "phone_number": "01 53 66 49 46",
    "website": "http://www.payet.fr/",
    "address": "74, avenue Barbier, 46673 Gomez",
    "birthdate": "1975-12-09",
    "age": 47,
    "interests": [
        "Cuisine",
        "Cinéma",
        "Lecture",
        "Musique",
        "Sport",
        "Technologie",
        "Voyages",
        "Photo",
        "Art",
        "Animaux"
    ],
    "user_image_url": "https://thispersondoesnotexist.com/",
    "background_image_url": "https://source.unsplash.com/random/1920x1080",
    "user_image_path": "./random_people/user_1015024047c246d78d93c6b5e85d4723.png"
}